{
  "format_version": "1.21.40",
  "minecraft:recipe_shaped": {
    "description": {
      "identifier": "lamp:pale_oak_street_lamp"
    },
    "tags": ["crafting_table"],
    "pattern": ["PPP", "G#G", "PPP"],
    "key": {
      "P": {
        "item": "minecraft:pale_oak_planks"
      },
      "G": {
        "item": "minecraft:glass"
      },
      "#": {
        "item": "minecraft:glowstone_dust"
      }
    },
    "result": {
      "item": "lamp:pale_oak_street_lamp"
    },
    "unlock": [
      {
        "item": "minecraft:pale_oak_planks"
      }
    ]
  }
}
